{
  "crawl_time": "2026-02-28T09:00:00+08:00",
  "activities": [
    {
      "title": "【账号经验值】2倍",
      "description": "",
      "image_url": "https://cdnimg-v2.gamekee.com/wiki2.0/images/w_793/h_444/829/191981/2026/1/11/630791.png",
      "progress": "17小时后结束",
      "tags": [
        "资源翻倍",
        "其他"
      ],
      "start_time": null,
      "end_time": "2026-03-01T02:00:00+08:00"
    },
    {
      "title": "【特别依赖】2倍掉落",
      "description": "",
      "image_url": "https://cdnimg-v2.gamekee.com/wiki2.0/images/w_798/h_443/829/191981/2026/1/11/385019.png",
      "progress": "3天后结束",
      "tags": [
        "资源翻倍",
        "多倍活动"
      ],
      "start_time": null,
      "end_time": "2026-03-03T09:00:00+08:00"
    },
    {
      "title": "【活动】情人节的约定",
      "description": "",
      "image_url": "https://cdnimg-v2.gamekee.com/wiki2.0/images/w_796/h_446/829/191981/2026/1/11/877172.png",
      "progress": "4天后结束",
      "tags": [
        "其他",
        "活动"
      ],
      "start_time": null,
      "end_time": "2026-03-04T09:00:00+08:00"
    },
    {
      "title": "合同火力演习 S49 - 射击演习(市街/轻装甲)",
      "description": "",
      "image_url": "https://cdnimg-v2.gamekee.com/wiki2.0/images/w_799/h_447/829/191981/2026/1/11/465021.png",
      "progress": "4天后结束",
      "tags": [
        "其他",
        "战术测试"
      ],
      "start_time": null,
      "end_time": "2026-03-04T09:00:00+08:00"
    },
    {
      "title": "制约解除作战 - 赛特的愤怒（特殊装甲）",
      "description": "",
      "image_url": "https://cdnimg-v2.gamekee.com/wiki2.0/images/w_802/h_444/829/191981/2026/1/11/807705.png",
      "progress": "17天后结束",
      "tags": [
        "其他",
        "爬塔"
      ],
      "start_time": null,
      "end_time": "2026-03-17T09:00:00+08:00"
    },
    {
      "title": "总力战 S86 - 比纳(室外战)",
      "description": "",
      "image_url": "https://cdnimg-v2.gamekee.com/wiki2.0/images/w_797/h_446/829/191981/2026/1/11/454070.png",
      "progress": "26.02.18-26.02.25",
      "tags": [
        "总力战",
        "总力大决"
      ],
      "start_time": null,
      "end_time": null
    },
    {
      "title": "【指名手配】2倍掉落",
      "description": "",
      "image_url": "https://cdnimg-v2.gamekee.com/wiki2.0/images/w_798/h_443/829/191981/2026/1/11/324187.png",
      "progress": "26.02.17-26.02.24",
      "tags": [
        "资源翻倍",
        "多倍活动"
      ],
      "start_time": null,
      "end_time": null
    },
    {
      "title": "【账号经验值】2倍",
      "description": "",
      "image_url": "https://cdnimg-v2.gamekee.com/wiki2.0/images/w_793/h_444/829/191981/2026/1/11/113564.png",
      "progress": "26.02.20-26.02.23",
      "tags": [
        "资源翻倍",
        "其他"
      ],
      "start_time": null,
      "end_time": null
    },
    {
      "title": "【联合作战】神名十文字·决战",
      "description": "",
      "image_url": "https://cdnimg-v2.gamekee.com/wiki2.0/images/w_1280/h_720/829/191981/2026/1/11/325350.png",
      "progress": "26.02.12-26.02.18",
      "tags": [
        "其他",
        "活动"
      ],
      "start_time": null,
      "end_time": null
    },
    {
      "title": "【Normal关卡】2倍掉落",
      "description": "",
      "image_url": "https://cdnimg-v2.gamekee.com/wiki2.0/images/w_798/h_443/829/191981/2026/1/11/38566.png",
      "progress": "26.02.11-26.02.17",
      "tags": [
        "资源翻倍",
        "多倍活动"
      ],
      "start_time": null,
      "end_time": null
    }
  ]
}